pychubby/__init__.py
pychubby/actions.py
pychubby/base.py
pychubby/cli.py
pychubby/data.py
pychubby/detect.py
pychubby/reference.py
pychubby/utils.py
pychubby/visualization.py
pychubby_cu-0.3.18.dist-info/LICENSE
pychubby_cu-0.3.18.dist-info/METADATA
pychubby_cu-0.3.18.dist-info/WHEEL
pychubby_cu-0.3.18.dist-info/entry_points.txt
pychubby_cu-0.3.18.dist-info/top_level.txt
pychubby_cu-0.3.18.dist-info/RECORD
